semantic_dom_ssg/__init__.py
semantic_dom_ssg/certification.py
semantic_dom_ssg/cli.py
semantic_dom_ssg/config.py
semantic_dom_ssg/parser.py
semantic_dom_ssg/security.py
semantic_dom_ssg/summary.py
semantic_dom_ssg/types.py
semantic_dom_ssg-0.2.0.dist-info/METADATA
semantic_dom_ssg-0.2.0.dist-info/WHEEL
semantic_dom_ssg-0.2.0.dist-info/entry_points.txt
semantic_dom_ssg-0.2.0.dist-info/licenses/LICENSE
semantic_dom_ssg-0.2.0.dist-info/RECORD
