Metadata-Version: 2.4
Name: semantic-dom-ssg
Version: 0.2.0
Summary: Machine-readable web semantics for AI agents. O(1) lookup, deterministic navigation, token-efficient serialization.
Project-URL: Homepage, https://github.com/gorgalxandr/semantic-dom-ssg
Project-URL: Documentation, https://github.com/gorgalxandr/semantic-dom-ssg#readme
Project-URL: Repository, https://github.com/gorgalxandr/semantic-dom-ssg
Project-URL: Issues, https://github.com/gorgalxandr/semantic-dom-ssg/issues
Author-email: George Alexander <info@gorgalxandr.com>
License-Expression: MIT
License-File: LICENSE
Keywords: accessibility,ai-agent,html-parser,llm,semantic-dom,token-optimization,web-automation
Classifier: Development Status :: 4 - Beta
Classifier: Intended Audience :: Developers
Classifier: License :: OSI Approved :: MIT License
Classifier: Programming Language :: Python :: 3
Classifier: Programming Language :: Python :: 3.10
Classifier: Programming Language :: Python :: 3.11
Classifier: Programming Language :: Python :: 3.12
Classifier: Topic :: Internet :: WWW/HTTP :: Browsers
Classifier: Topic :: Software Development :: Libraries :: Python Modules
Classifier: Topic :: Text Processing :: Markup :: HTML
Requires-Python: >=3.10
Requires-Dist: beautifulsoup4>=4.12.0
Requires-Dist: lxml>=5.0.0
Provides-Extra: dev
Requires-Dist: black>=23.0.0; extra == 'dev'
Requires-Dist: mypy>=1.0.0; extra == 'dev'
Requires-Dist: pytest-cov>=4.0.0; extra == 'dev'
Requires-Dist: pytest>=7.0.0; extra == 'dev'
Requires-Dist: ruff>=0.1.0; extra == 'dev'
